[
	{
		"ship": "Apocalypse Imperial Issue",
		"extenders": 3,
		"hardners": 2,
		"hasCommandBurst": "no",
		"rawShieldHp": "58,619",
		"effectiveShieldHp": 220907.71834635147,
		"effectiveHpPerSec": 8260.079457877671
	},
	{
		"ship": "Megathron Federate Issue",
		"extenders": 3,
		"hardners": 2,
		"hasCommandBurst": "no",
		"rawShieldHp": "58,619",
		"effectiveShieldHp": 220907.71834635147,
		"effectiveHpPerSec": 8260.079457877671
	},
	{
		"ship": "Rattlesnake",
		"extenders": 4,
		"hardners": 3,
		"hasCommandBurst": "no",
		"rawShieldHp": "73,332",
		"effectiveShieldHp": 364001.7526193233,
		"effectiveHpPerSec": 7453.156647760107
	},
	{
		"ship": "Tempest Tribal Issue",
		"extenders": 3,
		"hardners": 3,
		"hasCommandBurst": "no",
		"rawShieldHp": "61,613",
		"effectiveShieldHp": 305832.20120143454,
		"effectiveHpPerSec": 7051.914192921675
	},
	{
		"ship": "Nightmare",
		"extenders": 4,
		"hardners": 3,
		"hasCommandBurst": "no",
		"rawShieldHp": "68,406",
		"effectiveShieldHp": 339549.72648917034,
		"effectiveHpPerSec": 6502.512703771422
	},
	{
		"ship": "Thunderchild",
		"extenders": 4,
		"hardners": 3,
		"hasCommandBurst": "no",
		"rawShieldHp": "72,263",
		"effectiveShieldHp": 400085.2018593855,
		"effectiveHpPerSec": 6062.070494809249
	},
	{
		"ship": "Barghest",
		"extenders": 3,
		"hardners": 3,
		"hasCommandBurst": "no",
		"rawShieldHp": "58,665",
		"effectiveShieldHp": 291201.4020954587,
		"effectiveHpPerSec": 5962.525318208087
	},
	{
		"ship": "Bhaalgorn",
		"extenders": 3,
		"hardners": 2,
		"hasCommandBurst": "no",
		"rawShieldHp": "54,411",
		"effectiveShieldHp": 205051.3356043329,
		"effectiveHpPerSec": 5673.716834833904
	},
	{
		"ship": "Dominix Navy Issue",
		"extenders": 3,
		"hardners": 3,
		"hasCommandBurst": "no",
		"rawShieldHp": "54,859",
		"effectiveShieldHp": 272306.6546312495,
		"effectiveHpPerSec": 5556.5294431468
	},
	{
		"ship": "Vindicator",
		"extenders": 3,
		"hardners": 2,
		"hasCommandBurst": "no",
		"rawShieldHp": "53,179",
		"effectiveShieldHp": 200410.25599188916,
		"effectiveHpPerSec": 5545.299375609269
	},
	{
		"ship": "Machariel",
		"extenders": 3,
		"hardners": 3,
		"hasCommandBurst": "no",
		"rawShieldHp": "54,456",
		"effectiveShieldHp": 270306.03431150975,
		"effectiveHpPerSec": 5534.6799900313235
	},
	{
		"ship": "Marshal",
		"extenders": 4,
		"hardners": 3,
		"hasCommandBurst": "no",
		"rawShieldHp": "54,961",
		"effectiveShieldHp": 329647.6663207612,
		"effectiveHpPerSec": 5472.758834139359
	},
	{
		"ship": "Nestor",
		"extenders": 3,
		"hardners": 3,
		"hasCommandBurst": "no",
		"rawShieldHp": "53,515",
		"effectiveShieldHp": 265637.9202321169,
		"effectiveHpPerSec": 5439.097523098217
	},
	{
		"ship": "Armageddon Imperial Issue",
		"extenders": 2,
		"hardners": 2,
		"hasCommandBurst": "no",
		"rawShieldHp": "38,401",
		"effectiveShieldHp": 144717.30064256417,
		"effectiveHpPerSec": 5411.202520153567
	},
	{
		"ship": "Raven State Issue",
		"extenders": 3,
		"hardners": 3,
		"hasCommandBurst": "no",
		"rawShieldHp": "63,815",
		"effectiveShieldHp": 316764.88395880046,
		"effectiveHpPerSec": 5404.960927764963
	},
	{
		"ship": "Scorpion",
		"extenders": 5,
		"hardners": 3,
		"hasCommandBurst": "no",
		"rawShieldHp": "71,653",
		"effectiveShieldHp": 355665.83462040755,
		"effectiveHpPerSec": 5389.030516609446
	},
	{
		"ship": "Hyperion",
		"extenders": 3,
		"hardners": 2,
		"hasCommandBurst": "no",
		"rawShieldHp": "50,381",
		"effectiveShieldHp": 189862.34778178972,
		"effectiveHpPerSec": 5253.441513735097
	},
	{
		"ship": "Dominix",
		"extenders": 3,
		"hardners": 2,
		"hasCommandBurst": "no",
		"rawShieldHp": "49,709",
		"effectiveShieldHp": 187330.8498113659,
		"effectiveHpPerSec": 5183.395626885295
	},
	{
		"ship": "Rattlesnake Victory Edition",
		"extenders": 4,
		"hardners": 3,
		"hasCommandBurst": "no",
		"rawShieldHp": "50,940",
		"effectiveShieldHp": 252856.179300446,
		"effectiveHpPerSec": 5177.383625543282
	},
	{
		"ship": "响尾蛇级YC117年特别版",
		"extenders": 4,
		"hardners": 3,
		"hasCommandBurst": "no",
		"rawShieldHp": "50,940",
		"effectiveShieldHp": 252856.179300446,
		"effectiveHpPerSec": 5177.383625543282
	},
	{
		"ship": "Megathron",
		"extenders": 2,
		"hardners": 2,
		"hasCommandBurst": "no",
		"rawShieldHp": "36,498",
		"effectiveShieldHp": 137544.72305969658,
		"effectiveHpPerSec": 5143.0088092421665
	},
	{
		"ship": "Typhoon",
		"extenders": 3,
		"hardners": 2,
		"hasCommandBurst": "no",
		"rawShieldHp": "48,141",
		"effectiveShieldHp": 181424.0212137102,
		"effectiveHpPerSec": 5019.9552242357595
	},
	{
		"ship": "Vargur",
		"extenders": 3,
		"hardners": 3,
		"hasCommandBurst": "no",
		"rawShieldHp": "49,465",
		"effectiveShieldHp": 279230.96441288013,
		"effectiveHpPerSec": 4718.384143973712
	},
	{
		"ship": "Kronos",
		"extenders": 3,
		"hardners": 2,
		"hasCommandBurst": "no",
		"rawShieldHp": "48,447",
		"effectiveShieldHp": 199798.73061024022,
		"effectiveHpPerSec": 4562.372327421459
	},
	{
		"ship": "Raven",
		"extenders": 4,
		"hardners": 3,
		"hasCommandBurst": "no",
		"rawShieldHp": "60,457",
		"effectiveShieldHp": 300093.04796096886,
		"effectiveHpPerSec": 4546.994498389219
	},
	{
		"ship": "Scorpion Navy Issue",
		"extenders": 5,
		"hardners": 3,
		"hasCommandBurst": "no",
		"rawShieldHp": "81,729",
		"effectiveShieldHp": 405681.34261390235,
		"effectiveHpPerSec": 4533.084758855198
	},
	{
		"ship": "Megathron Navy Issue",
		"extenders": 2,
		"hardners": 2,
		"hasCommandBurst": "no",
		"rawShieldHp": "42,543",
		"effectiveShieldHp": 160328.20479351134,
		"effectiveHpPerSec": 4421.031153319993
	},
	{
		"ship": "Tempest Fleet Issue",
		"extenders": 3,
		"hardners": 2,
		"hasCommandBurst": "no",
		"rawShieldHp": "56,426",
		"effectiveShieldHp": 212645.8295156045,
		"effectiveHpPerSec": 4339.125734058486
	},
	{
		"ship": "Leshak",
		"extenders": 2,
		"hardners": 2,
		"hasCommandBurst": "no",
		"rawShieldHp": "30,228",
		"effectiveShieldHp": 113917.40866907383,
		"effectiveHpPerSec": 4259.547173298726
	},
	{
		"ship": "Typhoon Fleet Issue",
		"extenders": 3,
		"hardners": 2,
		"hasCommandBurst": "no",
		"rawShieldHp": "54,859",
		"effectiveShieldHp": 206739.0009179488,
		"effectiveHpPerSec": 4218.594463667973
	},
	{
		"ship": "Apocalypse Navy Issue",
		"extenders": 2,
		"hardners": 2,
		"hasCommandBurst": "no",
		"rawShieldHp": "40,304",
		"effectiveShieldHp": 151889.8782254318,
		"effectiveHpPerSec": 4188.345303145257
	},
	{
		"ship": "Armageddon Navy Issue",
		"extenders": 3,
		"hardners": 2,
		"hasCommandBurst": "no",
		"rawShieldHp": "52,620",
		"effectiveShieldHp": 198300.67434986928,
		"effectiveHpPerSec": 4046.406934538668
	},
	{
		"ship": "Abaddon",
		"extenders": 2,
		"hardners": 2,
		"hasCommandBurst": "no",
		"rawShieldHp": "38,065",
		"effectiveShieldHp": 143451.55165735225,
		"effectiveHpPerSec": 3969.2669214887396
	},
	{
		"ship": "马克瑞级YC117年特别版",
		"extenders": 3,
		"hardners": 2,
		"hasCommandBurst": "no",
		"rawShieldHp": "37,662",
		"effectiveShieldHp": 141932.65287509793,
		"effectiveHpPerSec": 3927.239389378859
	},
	{
		"ship": "Armageddon",
		"extenders": 2,
		"hardners": 2,
		"hasCommandBurst": "no",
		"rawShieldHp": "37,617",
		"effectiveShieldHp": 141763.88634373635,
		"effectiveHpPerSec": 3922.5696635888726
	},
	{
		"ship": "Maelstrom",
		"extenders": 3,
		"hardners": 3,
		"hasCommandBurst": "no",
		"rawShieldHp": "51,500",
		"effectiveShieldHp": 255634.81863341795,
		"effectiveHpPerSec": 3873.3656838130396
	},
	{
		"ship": "Praxis",
		"extenders": 4,
		"hardners": 3,
		"hasCommandBurst": "no",
		"rawShieldHp": "36,946",
		"effectiveShieldHp": 183390.19597614766,
		"effectiveHpPerSec": 3806.7207545039287
	},
	{
		"ship": "Raven Navy Issue",
		"extenders": 4,
		"hardners": 3,
		"hasCommandBurst": "no",
		"rawShieldHp": "68,294",
		"effectiveShieldHp": 338993.99862257595,
		"effectiveHpPerSec": 3787.9201409611933
	},
	{
		"ship": "Tempest",
		"extenders": 3,
		"hardners": 2,
		"hasCommandBurst": "no",
		"rawShieldHp": "48,813",
		"effectiveShieldHp": 183955.51918413406,
		"effectiveHpPerSec": 3766.6008222033147
	},
	{
		"ship": "Apocalypse",
		"extenders": 2,
		"hardners": 2,
		"hasCommandBurst": "no",
		"rawShieldHp": "35,826",
		"effectiveShieldHp": 135013.22508927272,
		"effectiveHpPerSec": 3735.7806319894025
	},
	{
		"ship": "Megathron Quafe Edition",
		"extenders": 2,
		"hardners": 2,
		"hasCommandBurst": "no",
		"rawShieldHp": "25,302",
		"effectiveShieldHp": 95353.09021929884,
		"effectiveHpPerSec": 3565.3987450574523
	},
	{
		"ship": "Megathron Police Edition",
		"extenders": 2,
		"hardners": 2,
		"hasCommandBurst": "no",
		"rawShieldHp": "25,302",
		"effectiveShieldHp": 95353.09021929884,
		"effectiveHpPerSec": 3565.3987450574523
	},
	{
		"ship": "Megathron Inner Zone Shipping Edition",
		"extenders": 2,
		"hardners": 2,
		"hasCommandBurst": "no",
		"rawShieldHp": "25,302",
		"effectiveShieldHp": 95353.09021929884,
		"effectiveHpPerSec": 3565.3987450574523
	},
	{
		"ship": "万王宝座级YC117年特别版",
		"extenders": 2,
		"hardners": 2,
		"hasCommandBurst": "no",
		"rawShieldHp": "25,302",
		"effectiveShieldHp": 95353.09021929884,
		"effectiveHpPerSec": 3565.3987450574523
	},
	{
		"ship": "Rokh",
		"extenders": 4,
		"hardners": 3,
		"hasCommandBurst": "no",
		"rawShieldHp": "63,815",
		"effectiveShieldHp": 316764.88395880046,
		"effectiveHpPerSec": 3551.707924852913
	},
	{
		"ship": "Hyperion Aliastra Edition",
		"extenders": 3,
		"hardners": 2,
		"hasCommandBurst": "no",
		"rawShieldHp": "33,587",
		"effectiveShieldHp": 126574.89852119314,
		"effectiveHpPerSec": 3502.294342490064
	},
	{
		"ship": "Hyperion Inner Zone Shipping Edition",
		"extenders": 3,
		"hardners": 2,
		"hasCommandBurst": "no",
		"rawShieldHp": "33,587",
		"effectiveShieldHp": 126574.89852119314,
		"effectiveHpPerSec": 3502.294342490064
	},
	{
		"ship": "Dominix Quafe Edition",
		"extenders": 3,
		"hardners": 2,
		"hasCommandBurst": "no",
		"rawShieldHp": "32,915",
		"effectiveShieldHp": 124043.4005507693,
		"effectiveHpPerSec": 3432.2484556402633
	},
	{
		"ship": "多米尼克斯级YC117年特别版",
		"extenders": 3,
		"hardners": 2,
		"hasCommandBurst": "no",
		"rawShieldHp": "32,915",
		"effectiveShieldHp": 124043.4005507693,
		"effectiveHpPerSec": 3432.2484556402633
	},
	{
		"ship": "Paladin",
		"extenders": 2,
		"hardners": 2,
		"hasCommandBurst": "no",
		"rawShieldHp": "36,437",
		"effectiveShieldHp": 147486.03776060915,
		"effectiveHpPerSec": 3367.8202824655605
	},
	{
		"ship": "Golem",
		"extenders": 4,
		"hardners": 3,
		"hasCommandBurst": "no",
		"rawShieldHp": "62,696",
		"effectiveShieldHp": 343810.3067997273,
		"effectiveHpPerSec": 3181.3543927827545
	},
	{
		"ship": "Sin",
		"extenders": 3,
		"hardners": 3,
		"hasCommandBurst": "no",
		"rawShieldHp": "42,493",
		"effectiveShieldHp": 243697.03530574206,
		"effectiveHpPerSec": 2993.906758401691
	},
	{
		"ship": "Raven Guristas Edition",
		"extenders": 4,
		"hardners": 3,
		"hasCommandBurst": "no",
		"rawShieldHp": "38,065",
		"effectiveShieldHp": 188947.4746420915,
		"effectiveHpPerSec": 2862.9224619487672
	},
	{
		"ship": "Raven Kaalakiota Edition",
		"extenders": 4,
		"hardners": 3,
		"hasCommandBurst": "no",
		"rawShieldHp": "38,065",
		"effectiveShieldHp": 188947.4746420915,
		"effectiveHpPerSec": 2862.9224619487672
	},
	{
		"ship": "Raven Nugoeihuvi Edition",
		"extenders": 4,
		"hardners": 3,
		"hasCommandBurst": "no",
		"rawShieldHp": "38,065",
		"effectiveShieldHp": 188947.4746420915,
		"effectiveHpPerSec": 2862.9224619487672
	},
	{
		"ship": "乌鸦级YC117年特别版",
		"extenders": 4,
		"hardners": 3,
		"hasCommandBurst": "no",
		"rawShieldHp": "38,065",
		"effectiveShieldHp": 188947.4746420915,
		"effectiveHpPerSec": 2862.9224619487672
	},
	{
		"ship": "Abaddon Tash-Murkon Edition",
		"extenders": 2,
		"hardners": 2,
		"hasCommandBurst": "no",
		"rawShieldHp": "26,869",
		"effectiveShieldHp": 101259.91881695454,
		"effectiveHpPerSec": 2801.835473992052
	},
	{
		"ship": "Abaddon Kador Edition",
		"extenders": 2,
		"hardners": 2,
		"hasCommandBurst": "no",
		"rawShieldHp": "26,869",
		"effectiveShieldHp": 101259.91881695454,
		"effectiveHpPerSec": 2801.835473992052
	},
	{
		"ship": "地狱天使级YC117年特别版",
		"extenders": 2,
		"hardners": 2,
		"hasCommandBurst": "no",
		"rawShieldHp": "26,869",
		"effectiveShieldHp": 101259.91881695454,
		"effectiveHpPerSec": 2801.835473992052
	},
	{
		"ship": "末日沙场级YC117年特别版",
		"extenders": 2,
		"hardners": 2,
		"hasCommandBurst": "no",
		"rawShieldHp": "26,422",
		"effectiveShieldHp": 99572.25350333862,
		"effectiveHpPerSec": 2755.1382160921844
	},
	{
		"ship": "Rokh Nugoeihuvi Edition",
		"extenders": 3,
		"hardners": 3,
		"hasCommandBurst": "no",
		"rawShieldHp": "35,826",
		"effectiveShieldHp": 177832.91731020377,
		"effectiveHpPerSec": 2694.515258304723
	},
	{
		"ship": "Rokh Wiyrkomi Edition",
		"extenders": 3,
		"hardners": 3,
		"hasCommandBurst": "no",
		"rawShieldHp": "35,826",
		"effectiveShieldHp": 177832.91731020377,
		"effectiveHpPerSec": 2694.515258304723
	},
	{
		"ship": "Maelstrom Nefantar Edition",
		"extenders": 3,
		"hardners": 3,
		"hasCommandBurst": "no",
		"rawShieldHp": "34,706",
		"effectiveShieldHp": 172275.6386442599,
		"effectiveHpPerSec": 2610.3116564827
	},
	{
		"ship": "Maelstrom Krusual Edition",
		"extenders": 3,
		"hardners": 3,
		"hasCommandBurst": "no",
		"rawShieldHp": "34,706",
		"effectiveShieldHp": 172275.6386442599,
		"effectiveHpPerSec": 2610.3116564827
	},
	{
		"ship": "Widow",
		"extenders": 5,
		"hardners": 3,
		"hasCommandBurst": "no",
		"rawShieldHp": "66,792",
		"effectiveShieldHp": 386127.5940139873,
		"effectiveHpPerSec": 2597.659977692927
	},
	{
		"ship": "Apocalypse Blood Raider Edition",
		"extenders": 2,
		"hardners": 2,
		"hasCommandBurst": "no",
		"rawShieldHp": "24,630",
		"effectiveShieldHp": 92821.59224887498,
		"effectiveHpPerSec": 2568.3491844927134
	},
	{
		"ship": "Apocalypse Kador Edition",
		"extenders": 2,
		"hardners": 2,
		"hasCommandBurst": "no",
		"rawShieldHp": "24,630",
		"effectiveShieldHp": 92821.59224887498,
		"effectiveHpPerSec": 2568.3491844927134
	},
	{
		"ship": "Apocalypse Tash-Murkon Edition",
		"extenders": 2,
		"hardners": 2,
		"hasCommandBurst": "no",
		"rawShieldHp": "24,630",
		"effectiveShieldHp": 92821.59224887498,
		"effectiveHpPerSec": 2568.3491844927134
	},
	{
		"ship": "灾难级YC117年特别版",
		"extenders": 2,
		"hardners": 2,
		"hasCommandBurst": "no",
		"rawShieldHp": "24,630",
		"effectiveShieldHp": 92821.59224887498,
		"effectiveHpPerSec": 2568.3491844927134
	},
	{
		"ship": "Panther",
		"extenders": 3,
		"hardners": 2,
		"hasCommandBurst": "no",
		"rawShieldHp": "43,700",
		"effectiveShieldHp": 201513.84150910698,
		"effectiveHpPerSec": 2475.6708724366954
	},
	{
		"ship": "Tempest Justice Edition",
		"extenders": 3,
		"hardners": 2,
		"hasCommandBurst": "no",
		"rawShieldHp": "32,019",
		"effectiveShieldHp": 120668.06992353746,
		"effectiveHpPerSec": 2470.75191548199
	},
	{
		"ship": "Tempest Krusual Edition",
		"extenders": 3,
		"hardners": 2,
		"hasCommandBurst": "no",
		"rawShieldHp": "32,019",
		"effectiveShieldHp": 120668.06992353746,
		"effectiveHpPerSec": 2470.75191548199
	},
	{
		"ship": "Tempest Nefantar Edition",
		"extenders": 3,
		"hardners": 2,
		"hasCommandBurst": "no",
		"rawShieldHp": "32,019",
		"effectiveShieldHp": 120668.06992353746,
		"effectiveHpPerSec": 2470.75191548199
	},
	{
		"ship": "Kronos Police Edition",
		"extenders": 2,
		"hardners": 2,
		"hasCommandBurst": "no",
		"rawShieldHp": "26,055",
		"effectiveShieldHp": 107454.77948786029,
		"effectiveHpPerSec": 2453.712848361121
	},
	{
		"ship": "Kronos Quafe Edition",
		"extenders": 2,
		"hardners": 2,
		"hasCommandBurst": "no",
		"rawShieldHp": "26,055",
		"effectiveShieldHp": 107454.77948786029,
		"effectiveHpPerSec": 2453.712848361121
	},
	{
		"ship": "Kronos Inner Zone Shipping Edition",
		"extenders": 2,
		"hardners": 2,
		"hasCommandBurst": "no",
		"rawShieldHp": "26,055",
		"effectiveShieldHp": 107454.77948786029,
		"effectiveHpPerSec": 2453.712848361121
	},
	{
		"ship": "Scorpion Ishukone Watch",
		"extenders": 5,
		"hardners": 3,
		"hasCommandBurst": "no",
		"rawShieldHp": "42,859",
		"effectiveShieldHp": 212742.73147536028,
		"effectiveHpPerSec": 2385.365561651614
	},
	{
		"ship": "Vargur Justice Edition",
		"extenders": 3,
		"hardners": 3,
		"hasCommandBurst": "no",
		"rawShieldHp": "33,689",
		"effectiveShieldHp": 190175.82144169408,
		"effectiveHpPerSec": 2378.0267741253515
	},
	{
		"ship": "Vargur Krusual Edition",
		"extenders": 3,
		"hardners": 3,
		"hasCommandBurst": "no",
		"rawShieldHp": "33,689",
		"effectiveShieldHp": 190175.82144169408,
		"effectiveHpPerSec": 2378.0267741253515
	},
	{
		"ship": "Vargur Nefantar Edition",
		"extenders": 3,
		"hardners": 3,
		"hasCommandBurst": "no",
		"rawShieldHp": "33,689",
		"effectiveShieldHp": 190175.82144169408,
		"effectiveHpPerSec": 2378.0267741253515
	},
	{
		"ship": "GFX Test Vargur 1/2",
		"extenders": 3,
		"hardners": 3,
		"hasCommandBurst": "no",
		"rawShieldHp": "33,689",
		"effectiveShieldHp": 190175.82144169408,
		"effectiveHpPerSec": 2378.0267741253515
	},
	{
		"ship": "GFX Test Vargur 2/2",
		"extenders": 3,
		"hardners": 3,
		"hasCommandBurst": "no",
		"rawShieldHp": "33,689",
		"effectiveShieldHp": 190175.82144169408,
		"effectiveHpPerSec": 2378.0267741253515
	},
	{
		"ship": "Paladin Blood Raider Edition",
		"extenders": 2,
		"hardners": 2,
		"hasCommandBurst": "no",
		"rawShieldHp": "25,241",
		"effectiveShieldHp": 102169.09878388567,
		"effectiveHpPerSec": 2333.015167741505
	},
	{
		"ship": "Paladin Kador Edition",
		"extenders": 2,
		"hardners": 2,
		"hasCommandBurst": "no",
		"rawShieldHp": "25,241",
		"effectiveShieldHp": 102169.09878388567,
		"effectiveHpPerSec": 2333.015167741505
	},
	{
		"ship": "Paladin Tash-Murkon Edition",
		"extenders": 2,
		"hardners": 2,
		"hasCommandBurst": "no",
		"rawShieldHp": "25,241",
		"effectiveShieldHp": 102169.09878388567,
		"effectiveHpPerSec": 2333.015167741505
	},
	{
		"ship": "Redeemer",
		"extenders": 2,
		"hardners": 2,
		"hasCommandBurst": "no",
		"rawShieldHp": "31,297",
		"effectiveShieldHp": 132061.73599657658,
		"effectiveHpPerSec": 2192.468220368912
	},
	{
		"ship": "Golem Guristas Edition",
		"extenders": 4,
		"hardners": 3,
		"hasCommandBurst": "no",
		"rawShieldHp": "40,304",
		"effectiveShieldHp": 221020.91151411043,
		"effectiveHpPerSec": 2045.1563953603427
	},
	{
		"ship": "Golem Kaalakiota Edition",
		"extenders": 4,
		"hardners": 3,
		"hasCommandBurst": "no",
		"rawShieldHp": "40,304",
		"effectiveShieldHp": 221020.91151411043,
		"effectiveHpPerSec": 2045.1563953603427
	},
	{
		"ship": "Golem Nugoeihuvi Edition",
		"extenders": 4,
		"hardners": 3,
		"hasCommandBurst": "no",
		"rawShieldHp": "40,304",
		"effectiveShieldHp": 221020.91151411043,
		"effectiveHpPerSec": 2045.1563953603427
	},
	{
		"ship": "Orca ORE Development Edition",
		"extenders": 2,
		"hardners": 2,
		"hasCommandBurst": "no",
		"rawShieldHp": "33,078",
		"effectiveShieldHp": 124657.0970284478,
		"effectiveHpPerSec": 911.1741205571905
	},
	{
		"ship": "Orca",
		"extenders": 3,
		"hardners": 2,
		"hasCommandBurst": "no",
		"rawShieldHp": "77,861",
		"effectiveShieldHp": 293423.62839003874,
		"effectiveHpPerSec": 750.6672947051933
	}
]